django_toggle_switch_widget/__init__.py
django_toggle_switch_widget/admin.py
django_toggle_switch_widget/apps.py
django_toggle_switch_widget/models.py
django_toggle_switch_widget/tests.py
django_toggle_switch_widget/views.py
django_toggle_switch_widget/widgets.py
django_toggle_switch_widget/migrations/__init__.py
django_toggle_switch_widget/static/django-toggle-switch-widget/css/django-toggle-switch-widget.css
django_toggle_switch_widget/templates/django-toggle-switch-widget/django-toggle-switch-widget.html
django_toggle_switch_widget-0.1.3.dist-info/LICENSE
django_toggle_switch_widget-0.1.3.dist-info/METADATA
django_toggle_switch_widget-0.1.3.dist-info/WHEEL
django_toggle_switch_widget-0.1.3.dist-info/top_level.txt
django_toggle_switch_widget-0.1.3.dist-info/RECORD
