Metadata-Version: 2.1
Name: django-toggle-switch-widget
Version: 0.1.3
Summary: Display toggle switch in stead of checkbox for BooleanField in django admin site.
Author: Zhou Wen
Author-email: zhouwen@zencore.cn
Maintainer: Zhou Wen
Maintainer-email: zhouwen@zencore.cn
License: MIT
Keywords: django admin extentions,django toggle switch widget
Classifier: Development Status :: 5 - Production/Stable
Classifier: Intended Audience :: Developers
Classifier: Topic :: Software Development :: Libraries :: Python Modules
Classifier: License :: OSI Approved :: MIT License
Classifier: Programming Language :: Python :: 3
Classifier: Programming Language :: Python :: 3 :: Only
License-File: LICENSE
